web_retriever/conf.py
web_retriever/scripts.py
web_retriever/version.py
web_retriever/web_retriever/fetch.py
web_retriever/web_retriever/init.py
web_retriever/web_retriever/ops.py
web_retriever/web_retriever/rss.py
web_retriever/web_retriever/throw.py
web_retriever/web_retriever/web.py
web_retriever/web_retriever/contracts/fetch.py
web_retriever/web_retriever/contracts/throw.py
web_retriever-0.3.0.dist-info/LICENSE
web_retriever-0.3.0.dist-info/METADATA
web_retriever-0.3.0.dist-info/WHEEL
web_retriever-0.3.0.dist-info/entry_points.txt
web_retriever-0.3.0.dist-info/top_level.txt
web_retriever-0.3.0.dist-info/RECORD
