Metadata-Version: 2.1
Name: web-retriever
Version: 0.3.0
Summary: UNKNOWN
Home-page: UNKNOWN
Author: nicholasmhughes
Author-email: nicholasmhughes@gmail.com
License: Apache Software License 2.0
Platform: UNKNOWN
Classifier: Environment :: Console
Classifier: Intended Audience :: Developers
Classifier: Intended Audience :: Information Technology
Classifier: Intended Audience :: System Administrators
Classifier: Operating System :: OS Independent
Classifier: Programming Language :: Python
Classifier: Programming Language :: Python :: 3.7
Classifier: Programming Language :: Python :: 3.8
Classifier: Programming Language :: Python :: 3.9
Classifier: Programming Language :: Python :: 3.10
Classifier: Development Status :: 5 - Production/Stable
Classifier: License :: OSI Approved :: Apache Software License
Requires-Python: >=3.7
License-File: LICENSE
Requires-Dist: PyYAML (>=6.0.1)
Requires-Dist: feedparser (>=6.0.10)
Requires-Dist: pop-aiohttp (>=1.2.0)
Requires-Dist: pop (>=17.0)
Requires-Dist: rule-engine (>=4.1.0)
